bggcohomology/__init__.py
bggcohomology/bggcomplex.py
bggcohomology/cohomology.cp37-win_amd64.pyd
bggcohomology/compute_maps.py
bggcohomology/compute_signs.py
bggcohomology/la_modules.py
bggcohomology/pbw.py
bggcohomology/quantum_center.py
bggcohomology/weight_set.py
bggcohomology-1.6.1.dist-info/LICENSE
bggcohomology-1.6.1.dist-info/METADATA
bggcohomology-1.6.1.dist-info/WHEEL
bggcohomology-1.6.1.dist-info/top_level.txt
bggcohomology-1.6.1.dist-info/RECORD
