Metadata-Version: 2.1
Name: bggcohomology
Version: 1.6.1
Summary: Tools for the BGG complex
Home-page: https://github.com/RikVoorhaar/bgg-cohomology
Author: Rik Voorhaar
License: UNKNOWN
Keywords: sagemath mathematics flag-varieties representation-theory algebra
Platform: UNKNOWN
Classifier: Development Status :: 5 - Production/Stable
Classifier: License :: OSI Approved :: GNU General Public License v3 (GPLv3)
Classifier: Operating System :: OS Independent
Classifier: Intended Audience :: Science/Research
Classifier: Programming Language :: Python :: 3
Classifier: Topic :: Scientific/Engineering :: Mathematics
Requires-Dist: tqdm
